avatarkit/__init__.py
avatarkit/avatar_session.py
avatarkit/errors.py
avatarkit/logid.py
avatarkit/proto/__init__.py
avatarkit/proto/generated/__init__.py
avatarkit/proto/generated/message_pb2.py
avatarkit/py.typed
avatarkit/session_config.py
avatarkit-0.1.3.dist-info/WHEEL
avatarkit-0.1.3.dist-info/METADATA
avatarkit-0.1.3.dist-info/RECORD
