Metadata-Version: 2.3
Name: avatarkit
Version: 0.1.3
Summary: Python SDK for avatar WebSocket services with audio streaming and animation frame reception
Keywords: avatar,websocket,sdk,audio,animation,protobuf
Author: 3DRX
Author-email: 3DRX <3drxkjy@gmail.com>
Classifier: Development Status :: 4 - Beta
Classifier: Intended Audience :: Developers
Classifier: Programming Language :: Python :: 3
Classifier: Programming Language :: Python :: 3.9
Classifier: Programming Language :: Python :: 3.10
Classifier: Programming Language :: Python :: 3.11
Classifier: Programming Language :: Python :: 3.12
Classifier: Programming Language :: Python :: 3.13
Classifier: Programming Language :: Python :: 3.14
Requires-Dist: aiohttp>=3.9.0
Requires-Dist: nanoid>=2.0.0
Requires-Dist: protobuf>=5.28.3
Requires-Dist: websockets>=10.0
Requires-Python: >=3.9
